package_translate_paper_title/__init__.py
package_translate_paper_title-0.0.1.dist-info/LICENSE
package_translate_paper_title-0.0.1.dist-info/METADATA
package_translate_paper_title-0.0.1.dist-info/WHEEL
package_translate_paper_title-0.0.1.dist-info/top_level.txt
package_translate_paper_title-0.0.1.dist-info/RECORD
