Metadata-Version: 2.1
Name: package-translate-paper-title
Version: 0.0.1
Summary: Paper Name Translate to save-able name. This is My First self-write Python Package
Home-page: 
Author: Loki Xun
Author-email: rongji.xun@gmail.com
License: MIT License
Keywords: self-testing package,
Classifier: Development Status :: 1 - Planning
Classifier: License :: OSI Approved :: MIT License
Classifier: Operating System :: OS Independent
Classifier: Programming Language :: Python :: 3
Classifier: Programming Language :: Python :: 3.6
Classifier: Programming Language :: Python :: 3.7
Classifier: Programming Language :: Python :: 3.8
Classifier: Programming Language :: Python :: 3.9
License-File: LICENSE
Requires-Dist: numpy
Requires-Dist: pypandoc
